bbd/__init__.py
bbd/census/__init__.py
bbd/census/api_key.py
bbd/census/datasets.py
bbd/census/geography.py
bbd/census/get_acs.py
bbd/census/get_shapefile.py
bbd/census/load.py
bbd/census/us.py
bbd/gis/__init__.py
bbd/gis/magic.py
bbd/gis/make_map.py
bbd/gis/trim_shapefile.py
bbd/gis/utils.py
bbd/working_directory/__init__.py
bbd/working_directory/working_directory.py
bbd-0.0.6.dist-info/LICENSE
bbd-0.0.6.dist-info/METADATA
bbd-0.0.6.dist-info/WHEEL
bbd-0.0.6.dist-info/top_level.txt
bbd-0.0.6.dist-info/RECORD
