Metadata-Version: 2.1
Name: bbd
Version: 0.0.6
Summary: A toolset for political campaign data analysis
Home-page: https://www.bluebonnetdata.org/
Author: Bluebonnet Data
Author-email: info@bluebonnetdata.org
License: UNKNOWN
Project-URL: Source, https://github.com/bluebonnet-data/bbd
Platform: UNKNOWN
Classifier: Programming Language :: Python :: 3
Classifier: License :: OSI Approved :: MIT License
Classifier: Operating System :: OS Independent
Requires-Python: >=3.6
Requires-Dist: shapely
Requires-Dist: pyshp
Requires-Dist: folium
Requires-Dist: branca
Requires-Dist: requests
Requires-Dist: us
Provides-Extra: dev
Requires-Dist: flake8 ; extra == 'dev'
Requires-Dist: black ; extra == 'dev'
